flint/__init__.py
flint/_version.py
flint/_version.pyi
flint/archive.py
flint/bandpass.py
flint/casa.py
flint/catalogue.py
flint/configuration.py
flint/containers.py
flint/convol.py
flint/exceptions.py
flint/flagging.py
flint/leakage.py
flint/logging.py
flint/masking.py
flint/ms.py
flint/naming.py
flint/options.py
flint/py.typed
flint/sclient.py
flint/sky_model.py
flint/summary.py
flint/utils.py
flint/validation.py
flint/bptools/__init__.py
flint/bptools/preflagger.py
flint/bptools/smoother.py
flint/calibrate/__init__.py
flint/calibrate/aocalibrate.py
flint/coadd/__init__.py
flint/coadd/linmos.py
flint/data/__init__.py
flint/data/aoflagger/ASKAP.lua
flint/data/aoflagger/ATCA.lua
flint/data/aoflagger/__init__.py
flint/data/cluster_configs/__init__.py
flint/data/cluster_configs/example_slurm.yaml
flint/data/models/1934-638.calibrate.txt
flint/data/models/__init__.py
flint/data/peel/known_sources.csv
flint/data/peel/peeling.csv
flint/data/source_counts/SKADS_1p4GHz.fits
flint/data/source_counts/__init__.py
flint/data/source_counts/de_zotti_1p4.txt
flint/data/tests/NVSS.fits.zip
flint/data/tests/SB38959.RACS_1357-18.noselfcal.linmos_comp.fits
flint/data/tests/SB38969.B1934-638.beam35.aocalibrate.bin
flint/data/tests/SB39400.RACS_0635-31.beam0-MFS-subimage_rms.fits
flint/data/tests/SB39400.RACS_0635-31.beam0.small.ms.zip
flint/data/tests/SB39433.B1934-638.beam0.calibrate.bin
flint/data/tests/SB56659.RACS_0940-04.beam17.round3-0000-image.sub.fits
flint/data/tests/SB56659.RACS_0940-04.beam17.round3-0001-image.sub.fits
flint/data/tests/SB56659.RACS_0940-04.beam17.round3-0002-image.sub.fits
flint/data/tests/__init__.py
flint/data/tests/scienceData.EMU_0529-60.SB50538.EMU_0529-60.beam08_averaged_cal.leakage.ms.zip
flint/data/tests/sub_cube_fits_examples.zip
flint/data/tests/test_config.yaml
flint/data/tests/test_config_2.yaml
flint/data/tests/test_config_pol.yaml
flint/imager/__init__.py
flint/imager/wsclean.py
flint/peel/__init__.py
flint/peel/potato.py
askap_flint-0.6.0.dist-info/METADATA
askap_flint-0.6.0.dist-info/WHEEL
askap_flint-0.6.0.dist-info/entry_points.txt
askap_flint-0.6.0.dist-info/licenses/LICENSE
askap_flint-0.6.0.dist-info/RECORD
