Metadata-Version: 2.4
Name: askap-flint
Version: 0.6.0
Summary: Pipeline for ASKAP processing, and profit along the way
Author-email: Tim Galvin <tim.galvin@csiro.au>
License: BSD 3-Clause License
License-File: LICENSE
Classifier: Development Status :: 1 - Planning
Classifier: Intended Audience :: Developers
Classifier: Intended Audience :: Science/Research
Classifier: License :: OSI Approved :: BSD License
Classifier: Operating System :: OS Independent
Classifier: Programming Language :: Python
Classifier: Programming Language :: Python :: 3
Classifier: Programming Language :: Python :: 3 :: Only
Classifier: Programming Language :: Python :: 3.11
Classifier: Programming Language :: Python :: 3.12
Classifier: Topic :: Scientific/Engineering
Classifier: Typing :: Typed
Requires-Python: <3.13,>=3.11
Requires-Dist: aegeantools==2.3.0
Requires-Dist: astropy>=6.1.3
Requires-Dist: astroquery>=0.4.8.dev0
Requires-Dist: configargparse>=1.7
Requires-Dist: crystalball>=0.4.3
Requires-Dist: dask-jobqueue
Requires-Dist: fitscube>=2.0.0
Requires-Dist: matplotlib
Requires-Dist: numpy>=2.0.0
Requires-Dist: pandas
Requires-Dist: prefect-dask>=0.2.4
Requires-Dist: prefect<3,>=2.10.0
Requires-Dist: pydantic<2.11
Requires-Dist: racs-tools>=4.2.1
Requires-Dist: radio-beam>=0.3.4
Requires-Dist: reproject
Requires-Dist: scikit-image
Requires-Dist: scipy
Requires-Dist: spython>=0.3.1
Provides-Extra: casa
Requires-Dist: fixms>=0.4.0; extra == 'casa'
Requires-Dist: python-casacore>=3.6.0; extra == 'casa'
Provides-Extra: dev
Requires-Dist: furo; extra == 'dev'
Requires-Dist: isort; extra == 'dev'
Requires-Dist: mypy; extra == 'dev'
Requires-Dist: myst-parser; extra == 'dev'
Requires-Dist: pre-commit; extra == 'dev'
Requires-Dist: pytest; extra == 'dev'
Requires-Dist: pytest-cov; extra == 'dev'
Requires-Dist: pytest-rerunfailures; extra == 'dev'
Requires-Dist: pytest-xdist; extra == 'dev'
Requires-Dist: ruff; extra == 'dev'
Requires-Dist: sphinx; extra == 'dev'
Requires-Dist: sphinx-argparse; extra == 'dev'
Requires-Dist: sphinx-autoapi; extra == 'dev'
Requires-Dist: sphinx-autodoc-typehints; extra == 'dev'
Requires-Dist: sphinx-copybutton; extra == 'dev'
